streamlit_chat_media/__init__.py
streamlit_chat_media/frontend/build/asset-manifest.json
streamlit_chat_media/frontend/build/bootstrap.min.css
streamlit_chat_media/frontend/build/bootstrap.min.css.map
streamlit_chat_media/frontend/build/index.html
streamlit_chat_media/frontend/build/precache-manifest.c29a79fbc77e2c50510d007756686dac.js
streamlit_chat_media/frontend/build/service-worker.js
streamlit_chat_media/frontend/build/static/css/2.95a91b17.chunk.css
streamlit_chat_media/frontend/build/static/css/2.95a91b17.chunk.css.map
streamlit_chat_media/frontend/build/static/js/2.e1848dfc.chunk.js
streamlit_chat_media/frontend/build/static/js/2.e1848dfc.chunk.js.LICENSE.txt
streamlit_chat_media/frontend/build/static/js/2.e1848dfc.chunk.js.map
streamlit_chat_media/frontend/build/static/js/main.87350243.chunk.js
streamlit_chat_media/frontend/build/static/js/main.87350243.chunk.js.map
streamlit_chat_media/frontend/build/static/js/runtime-main.11ec9aca.js
streamlit_chat_media/frontend/build/static/js/runtime-main.11ec9aca.js.map
streamlit_chat_media/frontend/build/static/media/KaTeX_AMS-Regular.10824af7.woff
streamlit_chat_media/frontend/build/static/media/KaTeX_AMS-Regular.56573229.ttf
streamlit_chat_media/frontend/build/static/media/KaTeX_AMS-Regular.66c67820.woff2
streamlit_chat_media/frontend/build/static/media/KaTeX_Caligraphic-Bold.497bf407.ttf
streamlit_chat_media/frontend/build/static/media/KaTeX_Caligraphic-Bold.a9e9b095.woff2
streamlit_chat_media/frontend/build/static/media/KaTeX_Caligraphic-Bold.de2ba279.woff
streamlit_chat_media/frontend/build/static/media/KaTeX_Caligraphic-Regular.08d95d99.woff2
streamlit_chat_media/frontend/build/static/media/KaTeX_Caligraphic-Regular.a25140fb.woff
streamlit_chat_media/frontend/build/static/media/KaTeX_Caligraphic-Regular.e6fb499f.ttf
streamlit_chat_media/frontend/build/static/media/KaTeX_Fraktur-Bold.40934fc0.woff
streamlit_chat_media/frontend/build/static/media/KaTeX_Fraktur-Bold.796f3797.woff2
streamlit_chat_media-0.0.4.dist-info/LICENSE
streamlit_chat_media-0.0.4.dist-info/METADATA
streamlit_chat_media-0.0.4.dist-info/WHEEL
streamlit_chat_media-0.0.4.dist-info/top_level.txt
streamlit_chat_media-0.0.4.dist-info/RECORD
