Metadata-Version: 2.1
Name: streamlit-chat-media
Version: 0.0.4
Summary: A streamlit component, to make chatbots with media support
Home-page: https://github.com/AI-Yash/st-chat
Author: Intelligenza Artificiale Italia
Author-email: ceo@intelligenzaartificialeitalia.net
Keywords: chat streamlit streamlit-component
Classifier: Programming Language :: Python :: 3
Classifier: Operating System :: OS Independent
Requires-Python: >=3.8
License-File: LICENSE
